<annotation>
	<folder>mergedImages</folder>
	<filename>150.jpeg</filename>
	<path>/home/zak/Desktop/Automatic Number Plate Recognition, OCR Web App in Python 7h/mergedImages/150.jpeg</path>
	<source>
		<database>Unknown</database>
	</source>
	<size>
		<width>500</width>
		<height>448</height>
		<depth>3</depth>
	</size>
	<segmented>0</segmented>
	<object>
		<name>number_plate</name>
		<pose>Unspecified</pose>
		<truncated>0</truncated>
		<difficult>0</difficult>
		<bndbox>
			<xmin>192</xmin>
			<ymin>316</ymin>
			<xmax>382</xmax>
			<ymax>359</ymax>
		</bndbox>
	</object>
</annotation>
